[

    {
        "primaryColor": "#FFCE00",
        "secondaryColor": "#333333",
        "bodyColor": "#243824",
        "textColor": "#FFFFFF",
        "actionColor": "#E94444",
        "successColor": "#38cc31",
        "borderGray": "#ccc",
        "primaryFont": "winlove",
        "secondaryFont": "georgia",
        "bodyRegularFont": "Poppins-Regular",
        "bodyMediumFont": "Poppins-Medium",
        "bodyBoldFont": "georgia",
        "tertiaryFont": "abrilfatfaceRegular",
        "headingFont": "BonheurRoyale-Regular",
        "bgImage": "https://ecsiondevstorage.blob.core.windows.net/wedding-storage/B9FC0751-896C-42FF-BC74-AE2958F7A5E8.png",
        "bgResponsiveImage": "https://ecsiondevstorage.blob.core.windows.net/wedding-storage/827EAE83-F658-421F-9721-DA94F99D507C.png"
        },
    
        {
        "primaryColor": "#FFCE00",
        "secondaryColor": "#333333",
        "bodyColor": "#243038",
        "textColor": "#FFFFFF",
        "actionColor": "#E94444",
        "successColor": "#38cc31",
        "borderGray": "#ccc",
       "primaryFont": "winlove",
        "secondaryFont": "georgia",
        "bodyRegularFont": "Poppins-Regular",
        "bodyMediumFont": "Poppins-Medium",
        "bodyBoldFont": "georgia",
        "tertiaryFont": "abrilfatfaceRegular",
        "headingFont": "BonheurRoyale-Regular",
         "bgImage": "https://ecsiondevstorage.blob.core.windows.net/wedding-storage/B9FC0751-896C-42FF-BC74-AE2958F7A5E8.png",
        "bgResponsiveImage": "https://ecsiondevstorage.blob.core.windows.net/wedding-storage/827EAE83-F658-421F-9721-DA94F99D507C.png"
        },
    
        
        {
        "primaryColor": "#FFCE00",
        "secondaryColor": "#333333",
        "bodyColor": "#1C190C",
        "textColor": "#FFFFFF",
        "actionColor": "#E94444",
        "successColor": "#38cc31",
        "borderGray": "#ccc",
       "primaryFont": "winlove",
        "secondaryFont": "georgia",
        "bodyRegularFont": "Poppins-Regular",
        "bodyMediumFont": "Poppins-Medium",
        "bodyBoldFont": "georgia",
        "tertiaryFont": "abrilfatfaceRegular",
        "headingFont": "BonheurRoyale-Regular",
         "bgImage": "https://ecsiondevstorage.blob.core.windows.net/wedding-storage/B9FC0751-896C-42FF-BC74-AE2958F7A5E8.png",
        "bgResponsiveImage": "https://ecsiondevstorage.blob.core.windows.net/wedding-storage/827EAE83-F658-421F-9721-DA94F99D507C.png"
        },
    
        {
        "primaryColor": "#FFCE00",
        "secondaryColor": "#333333",
        "bodyColor": "#383424",
        "textColor": "#FFFFFF",
        "actionColor": "#E94444",
        "successColor": "#38cc31",
        "borderGray": "#ccc",
        "primaryFont": "winlove",
        "secondaryFont": "georgia",
        "bodyRegularFont": "Poppins-Regular",
        "bodyMediumFont": "Poppins-Medium",
        "bodyBoldFont": "georgia",
        "tertiaryFont": "abrilfatfaceRegular",
        "headingFont": "BonheurRoyale-Regular",
        "bgImage": "https://ecsiondevstorage.blob.core.windows.net/wedding-storage/B9FC0751-896C-42FF-BC74-AE2958F7A5E8.png",
        "bgResponsiveImage": "https://ecsiondevstorage.blob.core.windows.net/wedding-storage/827EAE83-F658-421F-9721-DA94F99D507C.png"
        }
    ]