{
    "invitation-title": " ",
    "your-name": "Shamima",
    "partner-name": "Danish",
    "your-parent-name": "(D/O SHAMSUDDIN & FEROZA SULTANA)",
    "partner-parent-name": "(S/O YOUSUF MIR & SHAHANA MIR)",
    "your-grandparent-name": "YOUSUF ALI & RUKHSANA SULTANA",
    "invitation-full-date": "",
    "invitation-time": "",
    "invitation-venue":"",
    "invitation-address": "",
    "couple-img1": "",
    "couple-img2": "",
    "couple-img3": "",
    "invitation-description": "SOLICIT YOUR GRACIOUS PRESENCE ON THE AUSPICIOUS OCCASION OF THE WEDDING OF THEIR GRANDDAUGHTER",
    "invitation-message": "",
    "invitation-date": "",
    "invitation-month": "",
    "invitation-month-text": "",
    "invitation-year": "",
    "following-party": "#WEDDINGHASHTAG",
    "invitation-full-date-text": "",
    "invitation-week-day": "",
    "yourInitial": "",
    "partnerInitial": ""
  }